gevent_etcd
