Metadata-Version: 1.1
Name: gevent-etcd
Version: 2.3
Summary: a simple gevent requests etcd python client
Home-page: https://github.com/rfyiamcool
Author: ruifengyun
Author-email: rfyiamcool@163.com
License: MIT
Keywords: gevent etcd,fengyun
Platform: UNKNOWN
Classifier: Development Status :: 2 - Pre-Alpha
Classifier: Intended Audience :: Developers
Classifier: License :: OSI Approved :: MIT License
Classifier: Programming Language :: Python :: 2.7
Classifier: Programming Language :: Python :: 3.0
Classifier: Topic :: Software Development :: Libraries :: Python Modules
